{"cameraMode":{"drawMode":0,"name":"Shaded","section":"Shading Mode"},"sceneLighting":true,"audioPlay":false,"sceneViewState":{"m_AlwaysRefresh":false,"showFog":true,"showSkybox":true,"showFlares":true,"showImageEffects":true,"showParticleSystems":true,"showVisualEffectGraphs":true,"m_FxEnabled":true},"in2DMode":false,"pivot":{"x":36.519989013671878,"y":2.589996337890625,"z":1.2650146484375},"rotation":{"x":0.2639559805393219,"y":0.07370676845312119,"z":-0.020207948982715608,"w":0.9615765810012817},"size":4.552103519439697,"orthographic":false}